{"directed": true, "graph": [], "nodes": [{"tag": "", "word": "<s>", "id": 0, "shortest": 2, "sentences": "{}"}, {"tag": "", "word": "</s>", "id": 1, "shortest": -1, "sentences": "{}"}, {"tag": "DT", "word": "The", "id": 2, "shortest": 41, "sentences": "{43: 1, 237: 3}"}, {"tag": "NN", "word": "order", "id": 3, "shortest": -1, "sentences": "{43: 2}"}, {"tag": "VBD", "word": "made", "id": 4, "shortest": -1, "sentences": "{43: 3}"}, {"tag": "JJ", "word": "public", "id": 5, "shortest": -1, "sentences": "{43: 4}"}, {"tag": "IN", "word": "on", "id": 6, "shortest": -1, "sentences": "{43: 5}"}, {"tag": "NNP", "word": "March", "id": 7, "shortest": -1, "sentences": "{43: 6}"}, {"tag": "CD", "word": "12", "id": 8, "shortest": -1, "sentences": "{43: 7}"}, {"tag": "VBD", "word": "reclassified", "id": 9, "shortest": -1, "sentences": "{43: 8}"}, {"tag": "NN", "word": "broadband", "id": 10, "shortest": -1, "sentences": "{43: 9}"}, {"tag": "NNS", "word": "providers", "id": 11, "shortest": -1, "sentences": "{43: 10, 237: 22}"}, {"tag": "IN", "word": "as", "id": 12, "shortest": -1, "sentences": "{43: 11, 237: 8}"}, {"tag": "NNS", "word": "telecommunications", "id": 13, "shortest": -1, "sentences": "{43: 12}"}, {"tag": "NNS", "word": "services", "id": 14, "shortest": -1, "sentences": "{43: 13}"}, {"tag": "IN", "word": "under", "id": 15, "shortest": -1, "sentences": "{43: 14}"}, {"tag": "NNP", "word": "Title", "id": 16, "shortest": -1, "sentences": "{43: 15}"}, {"tag": "NNP", "word": "II", "id": 17, "shortest": -1, "sentences": "{43: 16}"}, {"tag": "IN", "word": "of", "id": 18, "shortest": -1, "sentences": "{43: 17, 237: 13}"}, {"tag": "DT", "word": "the", "id": 19, "shortest": -1, "sentences": "{43: 18, 237: 9}"}, {"tag": "NNPS", "word": "Communications", "id": 20, "shortest": -1, "sentences": "{43: 19}"}, {"tag": "NNP", "word": "Act", "id": 21, "shortest": -1, "sentences": "{43: 20}"}, {"tag": "IN", "word": "of", "id": 22, "shortest": -1, "sentences": "{43: 21, 237: 31}"}, {"tag": "CD", "word": "1934", "id": 23, "shortest": -1, "sentences": "{43: 22}"}, {"tag": "CC", "word": "and", "id": 24, "shortest": -1, "sentences": "{43: 23}"}, {"tag": "VBN", "word": "placed", "id": 25, "shortest": -1, "sentences": "{43: 24}"}, {"tag": "DT", "word": "the", "id": 26, "shortest": -1, "sentences": "{43: 25, 237: 14}"}, {"tag": "NN", "word": "agency", "id": 27, "shortest": -1, "sentences": "{43: 26}"}, {"tag": "IN", "word": "in", "id": 28, "shortest": -1, "sentences": "{43: 27, 237: 23}"}, {"tag": "DT", "word": "the", "id": 29, "shortest": -1, "sentences": "{43: 28, 237: 29}"}, {"tag": "NNS", "word": "crosshairs", "id": 30, "shortest": -1, "sentences": "{43: 29}"}, {"tag": "IN", "word": "of", "id": 31, "shortest": -1, "sentences": "{43: 30}"}, {"tag": "DT", "word": "both", "id": 32, "shortest": -1, "sentences": "{43: 31}"}, {"tag": "JJ", "word": "net", "id": 33, "shortest": 34, "sentences": "{43: 32, 237: 5}"}, {"tag": "NN", "word": "neutrality", "id": 34, "shortest": 35, "sentences": "{43: 33, 237: 6}"}, {"tag": "NNS", "word": "supporters", "id": 35, "shortest": 36, "sentences": "{43: 34}"}, {"tag": "CC", "word": "and", "id": 36, "shortest": 37, "sentences": "{43: 35}"}, {"tag": "NNS", "word": "critics", "id": 37, "shortest": 38, "sentences": "{43: 36}"}, {"tag": "VBP", "word": "alike", "id": 38, "shortest": 1, "sentences": "{43: 37}"}, {"tag": "NNP", "word": "Wheeler", "id": 39, "shortest": -1, "sentences": "{237: 1}"}, {"tag": "VBD", "word": "portrayed", "id": 40, "shortest": -1, "sentences": "{237: 2}"}, {"tag": "NNP", "word": "FCCs", "id": 41, "shortest": 33, "sentences": "{237: 4}"}, {"tag": "NNS", "word": "rules", "id": 42, "shortest": -1, "sentences": "{237: 7}"}, {"tag": "CD", "word": "21st", "id": 43, "shortest": -1, "sentences": "{237: 10}"}, {"tag": "NN", "word": "century", "id": 44, "shortest": -1, "sentences": "{237: 11}"}, {"tag": "NN", "word": "equivalent", "id": 45, "shortest": -1, "sentences": "{237: 12}"}, {"tag": "JJ", "word": "so-called", "id": 46, "shortest": -1, "sentences": "{237: 15}"}, {"tag": "JJ", "word": "must-carry", "id": 47, "shortest": -1, "sentences": "{237: 16}"}, {"tag": "NNS", "word": "rules", "id": 48, "shortest": -1, "sentences": "{237: 17}"}, {"tag": "WDT", "word": "which", "id": 49, "shortest": -1, "sentences": "{237: 18}"}, {"tag": "NN", "word": "require", "id": 50, "shortest": -1, "sentences": "{237: 19}"}, {"tag": "NN", "word": "cable", "id": 51, "shortest": -1, "sentences": "{237: 20}"}, {"tag": "NN", "word": "television", "id": 52, "shortest": -1, "sentences": "{237: 21}"}, {"tag": "DT", "word": "a", "id": 53, "shortest": -1, "sentences": "{237: 24}"}, {"tag": "JJ", "word": "particular", "id": 54, "shortest": -1, "sentences": "{237: 25}"}, {"tag": "NN", "word": "market", "id": 55, "shortest": -1, "sentences": "{237: 26}"}, {"tag": "TO", "word": "to", "id": 56, "shortest": -1, "sentences": "{237: 27}"}, {"tag": "VB", "word": "carry", "id": 57, "shortest": -1, "sentences": "{237: 28}"}, {"tag": "NNS", "word": "signals", "id": 58, "shortest": -1, "sentences": "{237: 30}"}, {"tag": "JJ", "word": "local", "id": 59, "shortest": -1, "sentences": "{237: 32}"}, {"tag": "NN", "word": "TV", "id": 60, "shortest": -1, "sentences": "{237: 33}"}, {"tag": "NNS", "word": "stations", "id": 61, "shortest": -1, "sentences": "{237: 34}"}], "links": [{"source": 0, "target": 0, "weight": 0.0}, {"source": 0, "target": 2, "weight": 1.0}, {"source": 0, "target": 39, "weight": 1.0}, {"source": 2, "target": 41, "weight": 1.0}, {"source": 2, "target": 2, "weight": 0.0}, {"source": 2, "target": 3, "weight": 1.0}, {"source": 3, "target": 4, "weight": 1.0}, {"source": 4, "target": 5, "weight": 1.0}, {"source": 5, "target": 6, "weight": 1.0}, {"source": 6, "target": 7, "weight": 1.0}, {"source": 7, "target": 8, "weight": 1.0}, {"source": 8, "target": 9, "weight": 1.0}, {"source": 9, "target": 10, "weight": 1.0}, {"source": 10, "target": 11, "weight": 1.0}, {"source": 11, "target": 28, "weight": 1.0}, {"source": 11, "target": 11, "weight": 0.0}, {"source": 11, "target": 12, "weight": 1.0}, {"source": 12, "target": 19, "weight": 1.0}, {"source": 12, "target": 12, "weight": 0.0}, {"source": 12, "target": 13, "weight": 1.0}, {"source": 13, "target": 14, "weight": 1.0}, {"source": 14, "target": 15, "weight": 1.0}, {"source": 15, "target": 16, "weight": 1.0}, {"source": 16, "target": 17, "weight": 1.0}, {"source": 17, "target": 18, "weight": 1.0}, {"source": 18, "target": 18, "weight": 0.0}, {"source": 18, "target": 19, "weight": 1.0}, {"source": 18, "target": 26, "weight": 1.0}, {"source": 19, "target": 43, "weight": 1.0}, {"source": 19, "target": 19, "weight": 0.0}, {"source": 19, "target": 20, "weight": 1.0}, {"source": 20, "target": 21, "weight": 1.0}, {"source": 21, "target": 22, "weight": 1.0}, {"source": 22, "target": 59, "weight": 1.0}, {"source": 22, "target": 22, "weight": 0.0}, {"source": 22, "target": 23, "weight": 1.0}, {"source": 23, "target": 24, "weight": 1.0}, {"source": 24, "target": 25, "weight": 1.0}, {"source": 25, "target": 26, "weight": 1.0}, {"source": 26, "target": 26, "weight": 0.0}, {"source": 26, "target": 27, "weight": 1.0}, {"source": 26, "target": 46, "weight": 1.0}, {"source": 27, "target": 28, "weight": 1.0}, {"source": 28, "target": 28, "weight": 0.0}, {"source": 28, "target": 29, "weight": 1.0}, {"source": 28, "target": 53, "weight": 1.0}, {"source": 29, "target": 58, "weight": 1.0}, {"source": 29, "target": 29, "weight": 0.0}, {"source": 29, "target": 30, "weight": 1.0}, {"source": 30, "target": 31, "weight": 1.0}, {"source": 31, "target": 32, "weight": 1.0}, {"source": 32, "target": 33, "weight": 1.0}, {"source": 33, "target": 34, "weight": 0.5}, {"source": 34, "target": 34, "weight": 0.0}, {"source": 34, "target": 35, "weight": 1.0}, {"source": 34, "target": 42, "weight": 1.0}, {"source": 35, "target": 36, "weight": 1.0}, {"source": 36, "target": 37, "weight": 1.0}, {"source": 37, "target": 38, "weight": 1.0}, {"source": 38, "target": 1, "weight": 1.0}, {"source": 39, "target": 40, "weight": 1.0}, {"source": 40, "target": 2, "weight": 1.0}, {"source": 41, "target": 33, "weight": 1.0}, {"source": 42, "target": 12, "weight": 1.0}, {"source": 43, "target": 44, "weight": 1.0}, {"source": 44, "target": 45, "weight": 1.0}, {"source": 45, "target": 18, "weight": 1.0}, {"source": 46, "target": 47, "weight": 1.0}, {"source": 47, "target": 48, "weight": 1.0}, {"source": 48, "target": 49, "weight": 1.0}, {"source": 49, "target": 50, "weight": 1.0}, {"source": 50, "target": 51, "weight": 1.0}, {"source": 51, "target": 52, "weight": 1.0}, {"source": 52, "target": 11, "weight": 1.0}, {"source": 53, "target": 54, "weight": 1.0}, {"source": 54, "target": 55, "weight": 1.0}, {"source": 55, "target": 56, "weight": 1.0}, {"source": 56, "target": 57, "weight": 1.0}, {"source": 57, "target": 29, "weight": 1.0}, {"source": 58, "target": 22, "weight": 1.0}, {"source": 59, "target": 60, "weight": 1.0}, {"source": 60, "target": 61, "weight": 1.0}, {"source": 61, "target": 1, "weight": 1.0}], "multigraph": false}